intervalmap/PlotIntervalMap.py
intervalmap/__init__.py
intervalmap-0.0.1.dist-info/LICENSE
intervalmap-0.0.1.dist-info/METADATA
intervalmap-0.0.1.dist-info/WHEEL
intervalmap-0.0.1.dist-info/top_level.txt
intervalmap-0.0.1.dist-info/RECORD
