Metadata-Version: 2.1
Name: intervalmap
Version: 0.0.1
Summary: A package to plot interval maps
Home-page: https://github.com/marciogameiro/intervalmap
Author: Marcio Gameiro
Author-email: marciogameiro@gmail.com
License: UNKNOWN
Platform: UNKNOWN
Classifier: Programming Language :: Python :: 3
Classifier: License :: OSI Approved :: MIT License
Classifier: Operating System :: OS Independent
Requires-Python: >=3.0
